CHANGELOG.txt
LICENSE.txt
MANIFEST.in
README.txt
ez_setup.py
setup.cfg
setup.py
TornadoPack.egg-info/PKG-INFO
TornadoPack.egg-info/SOURCES.txt
TornadoPack.egg-info/dependency_links.txt
TornadoPack.egg-info/entry_points.txt
TornadoPack.egg-info/not-zip-safe
TornadoPack.egg-info/requires.txt
TornadoPack.egg-info/top_level.txt
doc/Makefile
doc/index.txt
doc/source/api.rst
doc/source/conf.py
doc/source/index.rst
doc/source/manual.rst
example/README.txt
example/app.conf
example/run.py
test/README.txt
test/doc.py
tornadopack/__init__.py