Metadata-Version: 1.0
Name: TornadoPack
Version: 0.1.0
Summary: Serve a PipeStack application using Tornado
Home-page: http://jimmyg.org/work/code/tornadopack/index.html
Author: James Gardner
Author-email: james@<package hompage domain>
License: GNU AGPLv3
Platform: UNKNOWN
Classifier: Development Status :: 3 - Alpha
Classifier: License :: OSI Approved :: GNU Affero General Public License v3
Classifier: Programming Language :: Python
